{"id": "seattle-wine-tours-seattle", "rating": 5.0, "coordinates": {"longitude": -122.33048915863, "latitude": 47.600231132987}, "is_claimed": true, "photos": ["https://s3-media3.fl.yelpcdn.com/bphoto/yyppXre3Z-w0WNahcKDf7g/o.jpg", "https://s3-media2.fl.yelpcdn.com/bphoto/bcHPYf4-qpgFDl2WuX2uhQ/o.jpg", "https://s3-media2.fl.yelpcdn.com/bphoto/dMrdK_0xrSY7PUfcnqKknQ/o.jpg"], "review_count": 28, "term": "attractions", "url": "https://www.yelp.com/biz/seattle-wine-tours-seattle?adjust_creative=92p07_JjKyriZTQxAXRiKQ&utm_campaign=yelp_api_v3&utm_medium=api_v3_business_lookup&utm_source=92p07_JjKyriZTQxAXRiKQ", "categories": [{"alias": "winetours", "title": "Wine Tours"}], "location": {"address3": "", "zip_code": "98104", "address1": "321 3rd Ave S", "state": "WA", "city": "Seattle", "address2": "", "country": "US"}, "is_closed": false, "phone": "+12064449463", "image_url": "https://s3-media3.fl.yelpcdn.com/bphoto/yyppXre3Z-w0WNahcKDf7g/o.jpg", "name": "Seattle Wine Tours"}