{"location": {"address2": "Takapuna", "country": "NZ", "zip_code": "0622", "state": "AUK", "address3": "", "address1": "Corner of Anzac Street and Lake Road", "city": "Auckland"}, "term": "attractions", "url": "https://www.yelp.com/biz/potters-park-takapuna-auckland?adjust_creative=92p07_JjKyriZTQxAXRiKQ&utm_campaign=yelp_api_v3&utm_medium=api_v3_business_lookup&utm_source=92p07_JjKyriZTQxAXRiKQ", "coordinates": {"latitude": -36.7873428, "longitude": 174.7706944}, "id": "potters-park-takapuna-auckland", "name": "Potters Park Takapuna", "photos": ["https://s3-media2.fl.yelpcdn.com/bphoto/NGyVgX20rahoppGYs-QsZQ/o.jpg", "https://s3-media2.fl.yelpcdn.com/bphoto/kd4Np9FLEKCZ7I197g6Hlg/o.jpg", "https://s3-media3.fl.yelpcdn.com/bphoto/JgkbFfDNNMZkJdmQz_I0eQ/o.jpg"], "is_claimed": false, "review_count": 1, "categories": [{"alias": "playgrounds", "title": "Playgrounds"}], "is_closed": false, "image_url": "https://s3-media3.fl.yelpcdn.com/bphoto/NGyVgX20rahoppGYs-QsZQ/o.jpg", "rating": 4.0, "phone": ""}