{"price": "$", "rating": 3.0, "coordinates": {"longitude": -118.3093, "latitude": 33.99226}, "is_claimed": false, "photos": ["https://s3-media3.fl.yelpcdn.com/bphoto/JIdn0422IoWA_wkxJdtD4g/o.jpg", "https://s3-media4.fl.yelpcdn.com/bphoto/vnuBQcoRv7jc-oELJI5q7g/o.jpg", "https://s3-media2.fl.yelpcdn.com/bphoto/bFQOWz84nl28lf8PiTwMLA/o.jpg"], "review_count": 2, "id": "branco-motel-los-angeles", "term": "hotels", "url": "https://www.yelp.com/biz/branco-motel-los-angeles?adjust_creative=92p07_JjKyriZTQxAXRiKQ&utm_campaign=yelp_api_v3&utm_medium=api_v3_business_lookup&utm_source=92p07_JjKyriZTQxAXRiKQ", "categories": [{"alias": "hotels", "title": "Hotels"}], "location": {"address3": "", "zip_code": "90062", "address1": "5501 S Western Ave", "state": "CA", "city": "Los Angeles", "address2": "", "country": "US"}, "is_closed": false, "phone": "+13232903563", "image_url": "https://s3-media4.fl.yelpcdn.com/bphoto/JIdn0422IoWA_wkxJdtD4g/o.jpg", "name": "Branco Motel"}