{"price": "$$", "rating": 4.0, "coordinates": {"longitude": -71.0032, "latitude": 42.242614}, "is_claimed": true, "hours": [{"is_open_now": false, "open": [{"is_overnight": false, "day": 0, "end": "2130", "start": "1030"}, {"is_overnight": false, "day": 1, "end": "2130", "start": "1030"}, {"is_overnight": false, "day": 2, "end": "2130", "start": "1030"}, {"is_overnight": false, "day": 3, "end": "2130", "start": "1030"}, {"is_overnight": false, "day": 4, "end": "2130", "start": "1030"}, {"is_overnight": false, "day": 5, "end": "1700", "start": "1030"}, {"is_overnight": false, "day": 6, "end": "1700", "start": "1030"}], "hours_type": "REGULAR"}], "photos": ["https://s3-media4.fl.yelpcdn.com/bphoto/47VgyW6IMC1D81y1T5_wpw/o.jpg", "https://s3-media1.fl.yelpcdn.com/bphoto/G-UXHaLXFcz3DeUaIIzKaQ/o.jpg", "https://s3-media4.fl.yelpcdn.com/bphoto/p9_nM2g0YLE9h977O2g9Nw/o.jpg"], "review_count": 28, "id": "regina-russells-tea-room-quincy", "term": "attractions", "url": "https://www.yelp.com/biz/regina-russells-tea-room-quincy?adjust_creative=92p07_JjKyriZTQxAXRiKQ&utm_campaign=yelp_api_v3&utm_medium=api_v3_business_lookup&utm_source=92p07_JjKyriZTQxAXRiKQ", "categories": [{"alias": "tea", "title": "Tea Rooms"}, {"alias": "psychic_astrology", "title": "Psychics & Astrologers"}], "location": {"address3": "", "zip_code": "02169", "address1": "40 Franklin St", "state": "MA", "city": "Quincy", "address2": "", "country": "US"}, "is_closed": false, "phone": "+16174729606", "image_url": "https://s3-media2.fl.yelpcdn.com/bphoto/47VgyW6IMC1D81y1T5_wpw/o.jpg", "name": "Regina Russell's Tea Room"}