{"id": "newspaper-house-melbourne", "rating": 5.0, "coordinates": {"longitude": 144.9656525, "latitude": -37.815979}, "is_claimed": false, "photos": ["https://s3-media2.fl.yelpcdn.com/bphoto/rrVTI6YuJ7xBmXIN0pQiFQ/o.jpg", "https://s3-media3.fl.yelpcdn.com/bphoto/mWXDXGNQ7vpWvQ3KO5p4SQ/o.jpg"], "review_count": 1, "term": "attractions", "url": "https://www.yelp.com/biz/newspaper-house-melbourne?adjust_creative=92p07_JjKyriZTQxAXRiKQ&utm_campaign=yelp_api_v3&utm_medium=api_v3_business_lookup&utm_source=92p07_JjKyriZTQxAXRiKQ", "categories": [{"alias": "landmarks", "title": "Landmarks & Historical Buildings"}], "location": {"address3": "", "zip_code": "3000", "address1": "247-249 Collins st", "address2": "", "city": "Melbourne", "state": "VIC", "country": "AU"}, "is_closed": false, "phone": "", "image_url": "https://s3-media4.fl.yelpcdn.com/bphoto/rrVTI6YuJ7xBmXIN0pQiFQ/o.jpg", "name": "Newspaper House"}