{"price": "$$", "rating": 3.0, "coordinates": {"longitude": -115.135439426713, "latitude": 36.1219112477369}, "is_claimed": true, "hours": [{"is_open_now": true, "open": [{"is_overnight": false, "day": 0, "end": "2200", "start": "1100"}, {"is_overnight": false, "day": 1, "end": "2200", "start": "1100"}, {"is_overnight": false, "day": 2, "end": "2200", "start": "1100"}, {"is_overnight": false, "day": 3, "end": "2200", "start": "1100"}, {"is_overnight": false, "day": 4, "end": "2300", "start": "1100"}, {"is_overnight": false, "day": 5, "end": "2300", "start": "1000"}, {"is_overnight": false, "day": 6, "end": "2200", "start": "1000"}], "hours_type": "REGULAR"}], "photos": ["https://s3-media3.fl.yelpcdn.com/bphoto/3HBagEVPn12mLNA3cuwfqA/o.jpg", "https://s3-media1.fl.yelpcdn.com/bphoto/NXh9v40dwryC0BKqbRH7Eg/o.jpg", "https://s3-media1.fl.yelpcdn.com/bphoto/xlBfOV8m14W1Na8z0FTWsA/o.jpg"], "review_count": 154, "id": "johns-incredible-pizza-company-las-vegas-2", "term": "attractions", "url": "https://www.yelp.com/biz/johns-incredible-pizza-company-las-vegas-2?adjust_creative=92p07_JjKyriZTQxAXRiKQ&utm_campaign=yelp_api_v3&utm_medium=api_v3_business_lookup&utm_source=92p07_JjKyriZTQxAXRiKQ", "categories": [{"alias": "amusementparks", "title": "Amusement Parks"}, {"alias": "pizza", "title": "Pizza"}, {"alias": "arcades", "title": "Arcades"}], "location": {"address3": "", "zip_code": "89119", "address1": "3700 S. Maryland Pkwy", "state": "NV", "city": "Las Vegas", "address2": "", "country": "US"}, "is_closed": false, "phone": "+17023815555", "image_url": "https://s3-media4.fl.yelpcdn.com/bphoto/3HBagEVPn12mLNA3cuwfqA/o.jpg", "name": "John's Incredible Pizza Company"}