{"id": "mannies-seafood-houston", "rating": 4.0, "coordinates": {"longitude": -95.2635899, "latitude": 29.66928}, "is_claimed": false, "photos": ["https://s3-media2.fl.yelpcdn.com/bphoto/lviIq9Plgz9o8Pz87XXe4A/o.jpg", "https://s3-media2.fl.yelpcdn.com/bphoto/vIhWmRbEu_vLI5qffUPdEw/o.jpg", "https://s3-media3.fl.yelpcdn.com/bphoto/Q7rhNvrhKB6K2TfWfRYPQg/o.jpg"], "review_count": 84, "price": "$$", "term": "restaurants", "url": "https://www.yelp.com/biz/mannies-seafood-houston?adjust_creative=92p07_JjKyriZTQxAXRiKQ&utm_campaign=yelp_api_v3&utm_medium=api_v3_business_lookup&utm_source=92p07_JjKyriZTQxAXRiKQ", "categories": [{"alias": "seafood", "title": "Seafood"}], "location": {"address3": "", "zip_code": "77017", "address1": "8520 Gulf Freeway", "address2": "", "city": "Houston", "state": "TX", "country": "US"}, "is_closed": false, "phone": "+17136415003", "image_url": "https://s3-media3.fl.yelpcdn.com/bphoto/lviIq9Plgz9o8Pz87XXe4A/o.jpg", "name": "Mannie's Seafood"}