{"id": "flo-paris-french-bakery-cafe-houston-2", "rating": 4.5, "coordinates": {"longitude": -95.47993, "latitude": 29.73731}, "is_claimed": true, "hours": [{"is_open_now": false, "open": [{"is_overnight": false, "day": 0, "start": "0700", "end": "2000"}, {"is_overnight": false, "day": 1, "start": "0700", "end": "2000"}, {"is_overnight": false, "day": 2, "start": "0700", "end": "2000"}, {"is_overnight": false, "day": 3, "start": "0700", "end": "2000"}, {"is_overnight": false, "day": 4, "start": "0700", "end": "2000"}, {"is_overnight": false, "day": 5, "start": "0700", "end": "2000"}, {"is_overnight": false, "day": 6, "start": "0700", "end": "2000"}], "hours_type": "REGULAR"}], "photos": ["https://s3-media3.fl.yelpcdn.com/bphoto/7XJlcpFG8ldlABeMth_7Rw/o.jpg", "https://s3-media2.fl.yelpcdn.com/bphoto/287GZQ3Wk8NAso_E_zPj3g/o.jpg", "https://s3-media1.fl.yelpcdn.com/bphoto/I9yrx_wQ_wJEf9ZfYh2XOg/o.jpg"], "review_count": 218, "price": "$$", "term": "restaurants", "url": "https://www.yelp.com/biz/flo-paris-french-bakery-cafe-houston-2?adjust_creative=92p07_JjKyriZTQxAXRiKQ&utm_campaign=yelp_api_v3&utm_medium=api_v3_business_lookup&utm_source=92p07_JjKyriZTQxAXRiKQ", "categories": [{"alias": "bakeries", "title": "Bakeries"}, {"alias": "french", "title": "French"}, {"alias": "coffee", "title": "Coffee & Tea"}], "location": {"address3": "", "zip_code": "77057", "address1": "5757 Westheimer Rd", "address2": "Ste 105", "city": "Houston", "state": "TX", "country": "US"}, "is_closed": false, "phone": "+17137064442", "image_url": "https://s3-media2.fl.yelpcdn.com/bphoto/7XJlcpFG8ldlABeMth_7Rw/o.jpg", "name": "FLO Paris French Bakery-Cafe"}