{"price": "$$", "rating": 4.5, "coordinates": {"longitude": -111.9956512, "latitude": 33.5027504}, "is_claimed": true, "hours": [{"is_open_now": false, "open": [{"is_overnight": false, "day": 0, "end": "2100", "start": "1100"}, {"is_overnight": false, "day": 1, "end": "2100", "start": "1100"}, {"is_overnight": false, "day": 2, "end": "2100", "start": "1100"}, {"is_overnight": false, "day": 3, "end": "2100", "start": "1100"}, {"is_overnight": false, "day": 4, "end": "2100", "start": "1100"}, {"is_overnight": false, "day": 5, "end": "2100", "start": "1100"}, {"is_overnight": false, "day": 6, "end": "2100", "start": "1100"}], "hours_type": "REGULAR"}], "photos": ["https://s3-media2.fl.yelpcdn.com/bphoto/LpM2-TWAEO-mP-wZtZgkaw/o.jpg", "https://s3-media2.fl.yelpcdn.com/bphoto/tUjZvQrdyeP57pzjjllW1Q/o.jpg", "https://s3-media3.fl.yelpcdn.com/bphoto/g8p-_5uHZ8zxmvjFkUozdg/o.jpg"], "review_count": 334, "id": "ingos-tasty-food-phoenix", "term": "restaurants", "url": "https://www.yelp.com/biz/ingos-tasty-food-phoenix?adjust_creative=92p07_JjKyriZTQxAXRiKQ&utm_campaign=yelp_api_v3&utm_medium=api_v3_business_lookup&utm_source=92p07_JjKyriZTQxAXRiKQ", "categories": [{"alias": "newamerican", "title": "American (New)"}], "location": {"address3": "", "zip_code": "85018", "address1": "4502 N 40th St", "state": "AZ", "city": "Phoenix", "address2": "", "country": "US"}, "is_closed": false, "phone": "+16027952884", "image_url": "https://s3-media1.fl.yelpcdn.com/bphoto/LpM2-TWAEO-mP-wZtZgkaw/o.jpg", "name": "Ingo's Tasty Food"}