{"price": "\u00a3\u00a3", "rating": 4.0, "coordinates": {"longitude": -0.3100063, "latitude": 51.5252062}, "is_claimed": false, "photos": ["https://s3-media3.fl.yelpcdn.com/bphoto/ikIAP2kKUzOUwgdRqeMvew/o.jpg", "https://s3-media1.fl.yelpcdn.com/bphoto/Zxm3vZKS-jm05rNce0r6VQ/o.jpg", "https://s3-media2.fl.yelpcdn.com/bphoto/YXJb_qUaScjRCJEzW0MhOA/o.jpg"], "review_count": 18, "id": "caesar-hotel-london", "term": "attractions", "url": "https://www.yelp.com/biz/caesar-hotel-london?adjust_creative=92p07_JjKyriZTQxAXRiKQ&utm_campaign=yelp_api_v3&utm_medium=api_v3_business_lookup&utm_source=92p07_JjKyriZTQxAXRiKQ", "categories": [{"alias": "hotels", "title": "Hotels"}], "location": {"address3": "", "zip_code": "W2 3BD", "address1": "26-33 Queens Gardens", "state": "XGL", "city": "London", "address2": "Hyde Park", "country": "GB"}, "is_closed": false, "phone": "+442072620022", "image_url": "https://s3-media3.fl.yelpcdn.com/bphoto/ikIAP2kKUzOUwgdRqeMvew/o.jpg", "name": "Caesar Hotel"}