{"id": "casa-bella-inn-los-angeles", "rating": 4.5, "coordinates": {"longitude": -118.2815781, "latitude": 34.0481606}, "is_claimed": false, "photos": ["https://s3-media1.fl.yelpcdn.com/bphoto/3s8JUmv54pQTOtKKEaB1KA/o.jpg", "https://s3-media2.fl.yelpcdn.com/bphoto/tJo6v8IGdWp-aCjvvyIZRw/o.jpg", "https://s3-media1.fl.yelpcdn.com/bphoto/g8BohAlonZihf-12hQGV2g/o.jpg"], "review_count": 12, "price": "$$", "term": "hotels", "url": "https://www.yelp.com/biz/casa-bella-inn-los-angeles?adjust_creative=92p07_JjKyriZTQxAXRiKQ&utm_campaign=yelp_api_v3&utm_medium=api_v3_business_lookup&utm_source=92p07_JjKyriZTQxAXRiKQ", "categories": [{"alias": "hotels", "title": "Hotels"}], "location": {"address3": "", "zip_code": "90006", "address1": "1212 Alvarado Road", "address2": "", "city": "Los Angeles", "state": "CA", "country": "US"}, "is_closed": false, "phone": "+12133834774", "image_url": "https://s3-media1.fl.yelpcdn.com/bphoto/3s8JUmv54pQTOtKKEaB1KA/o.jpg", "name": "Casa Bella Inn"}