{"id": "chocolateria-san-churro-brisbane", "rating": 4.0, "coordinates": {"longitude": 153.020668029785, "latitude": -27.4779877228732}, "is_claimed": false, "hours": [{"is_open_now": true, "open": [{"is_overnight": false, "end": "2300", "day": 0, "start": "0800"}, {"is_overnight": false, "end": "2300", "day": 1, "start": "0800"}, {"is_overnight": false, "end": "2300", "day": 2, "start": "0800"}, {"is_overnight": false, "end": "2300", "day": 3, "start": "0800"}, {"is_overnight": true, "end": "0100", "day": 4, "start": "0800"}, {"is_overnight": true, "end": "0100", "day": 5, "start": "0900"}, {"is_overnight": false, "end": "2300", "day": 6, "start": "0900"}], "hours_type": "REGULAR"}], "photos": ["https://s3-media3.fl.yelpcdn.com/bphoto/2Wfq6OJd5DbJxEcQDQahwg/o.jpg", "https://s3-media3.fl.yelpcdn.com/bphoto/e7lpUSJHzYCsPZpNSegHsw/o.jpg", "https://s3-media2.fl.yelpcdn.com/bphoto/ubZWHmyjqnDKC3vfeDTzqQ/o.jpg"], "review_count": 21, "price": "$", "term": "restaurants", "url": "https://www.yelp.com/biz/chocolateria-san-churro-brisbane?adjust_creative=92p07_JjKyriZTQxAXRiKQ&utm_campaign=yelp_api_v3&utm_medium=api_v3_business_lookup&utm_source=92p07_JjKyriZTQxAXRiKQ", "categories": [{"title": "Cafes", "alias": "cafes"}, {"title": "Desserts", "alias": "desserts"}, {"title": "Ice Cream & Frozen Yogurt", "alias": "icecream"}, {"title": "Coffee & Tea", "alias": "coffee"}], "location": {"address3": "", "zip_code": "4101", "address1": "Shop 2/161 Grey St", "address2": "South Bank", "city": "Brisbane", "state": "QLD", "country": "AU"}, "is_closed": false, "phone": "+61738442022", "image_url": "https://s3-media2.fl.yelpcdn.com/bphoto/2Wfq6OJd5DbJxEcQDQahwg/o.jpg", "name": "Chocolateria San Churro"}