{"location": {"city": "Paris", "address2": "", "zip_code": "75015", "country": "FR", "address1": "24 rue Edgar Faure", "address3": "", "state": "75"}, "categories": [{"title": "Tours", "alias": "tours"}], "is_closed": false, "term": "attractions", "hours": [{"is_open_now": false, "hours_type": "REGULAR", "open": [{"day": 0, "end": "1800", "start": "0900", "is_overnight": false}, {"day": 1, "end": "1800", "start": "0900", "is_overnight": false}, {"day": 2, "end": "1800", "start": "0900", "is_overnight": false}, {"day": 3, "end": "1800", "start": "0900", "is_overnight": false}, {"day": 4, "end": "1800", "start": "0900", "is_overnight": false}, {"day": 5, "end": "1800", "start": "0900", "is_overnight": false}, {"day": 6, "end": "1800", "start": "0900", "is_overnight": false}]}], "id": "fat-tire-tours-paris-3", "phone": "+33156581054", "photos": ["https://s3-media1.fl.yelpcdn.com/bphoto/MfPur9r-NbdOw9ACawkLBw/o.jpg", "https://s3-media1.fl.yelpcdn.com/bphoto/SdompGPuesJ-K3v_8KMAbg/o.jpg", "https://s3-media3.fl.yelpcdn.com/bphoto/qytXG8Fqsukifii3Rvaksw/o.jpg"], "url": "https://www.yelp.com/biz/fat-tire-tours-paris-3?adjust_creative=92p07_JjKyriZTQxAXRiKQ&utm_campaign=yelp_api_v3&utm_medium=api_v3_business_lookup&utm_source=92p07_JjKyriZTQxAXRiKQ", "is_claimed": true, "review_count": 137, "rating": 4.5, "image_url": "https://s3-media2.fl.yelpcdn.com/bphoto/MfPur9r-NbdOw9ACawkLBw/o.jpg", "coordinates": {"latitude": 48.85225, "longitude": 2.29544}, "name": "Fat Tire Tours"}