{"id": "rokah-karate-los-angeles", "rating": 5.0, "coordinates": {"longitude": -118.3924668, "latitude": 34.0548574}, "is_claimed": true, "hours": [{"is_open_now": false, "open": [{"is_overnight": false, "day": 0, "end": "2000", "start": "1600"}, {"is_overnight": false, "day": 1, "end": "1000", "start": "0830"}, {"is_overnight": false, "day": 1, "end": "2100", "start": "1600"}, {"is_overnight": false, "day": 2, "end": "1300", "start": "1200"}, {"is_overnight": false, "day": 2, "end": "2130", "start": "1600"}, {"is_overnight": false, "day": 3, "end": "1000", "start": "0800"}, {"is_overnight": false, "day": 3, "end": "2100", "start": "1700"}, {"is_overnight": false, "day": 4, "end": "1300", "start": "1200"}, {"is_overnight": false, "day": 6, "end": "1200", "start": "0900"}], "hours_type": "REGULAR"}], "photos": ["https://s3-media1.fl.yelpcdn.com/bphoto/VsaLPP_WQp1BaXTPzE4CCA/o.jpg", "https://s3-media3.fl.yelpcdn.com/bphoto/qZp7spntfax8Ukfs7qcnvA/o.jpg", "https://s3-media2.fl.yelpcdn.com/bphoto/0dAp3V0hoMVMoNglh1X_mQ/o.jpg"], "review_count": 16, "term": "attractions", "url": "https://www.yelp.com/biz/rokah-karate-los-angeles?adjust_creative=92p07_JjKyriZTQxAXRiKQ&utm_campaign=yelp_api_v3&utm_medium=api_v3_business_lookup&utm_source=92p07_JjKyriZTQxAXRiKQ", "categories": [{"alias": "martialarts", "title": "Martial Arts"}, {"alias": "healthtrainers", "title": "Trainers"}], "location": {"address3": "", "zip_code": "90035", "address1": "9218 W Pico Blvd", "state": "CA", "city": "Los Angeles", "address2": "", "country": "US"}, "is_closed": false, "phone": "+13104632385", "image_url": "https://s3-media4.fl.yelpcdn.com/bphoto/VsaLPP_WQp1BaXTPzE4CCA/o.jpg", "name": "Rokah Karate"}