{"id": "mus\u00e9e-du-parfum-fragonard-paris-3", "categories": [{"title": "Museums", "alias": "museums"}, {"title": "Perfume", "alias": "perfume"}], "is_closed": false, "price": "\u20ac", "url": "https://www.yelp.com/biz/mus%C3%A9e-du-parfum-fragonard-paris-3?adjust_creative=92p07_JjKyriZTQxAXRiKQ&utm_campaign=yelp_api_v3&utm_medium=api_v3_business_lookup&utm_source=92p07_JjKyriZTQxAXRiKQ", "location": {"state": "75", "address2": "", "zip_code": "75009", "country": "FR", "address1": "9 rue Scribe", "address3": "", "city": "Paris"}, "phone": "+33147420456", "photos": ["https://s3-media3.fl.yelpcdn.com/bphoto/aI58hxqbyOX6irFfljXfQA/o.jpg", "https://s3-media1.fl.yelpcdn.com/bphoto/jIEqt19iVgJ2DoV4PQc_JA/o.jpg", "https://s3-media2.fl.yelpcdn.com/bphoto/A2-zsh3iDw5f6VgwoicekQ/o.jpg"], "hours": [{"is_open_now": false, "open": [{"start": "0900", "day": 0, "end": "1800", "is_overnight": false}, {"start": "0900", "day": 1, "end": "1800", "is_overnight": false}, {"start": "0900", "day": 2, "end": "1800", "is_overnight": false}, {"start": "0900", "day": 3, "end": "1800", "is_overnight": false}, {"start": "0900", "day": 4, "end": "1800", "is_overnight": false}, {"start": "0900", "day": 5, "end": "1800", "is_overnight": false}, {"start": "0900", "day": 6, "end": "1700", "is_overnight": false}], "hours_type": "REGULAR"}], "term": "attractions", "is_claimed": false, "rating": 3.5, "review_count": 28, "image_url": "https://s3-media2.fl.yelpcdn.com/bphoto/aI58hxqbyOX6irFfljXfQA/o.jpg", "coordinates": {"latitude": 48.871411209442, "longitude": 2.330198570256}, "name": "Mus\u00e9e du Parfum Fragonard"}