{"id": "city-of-sunnyvales-baylands-park-sunnyvale", "rating": 4.0, "coordinates": {"longitude": -121.997914684656, "latitude": 37.4127977683149}, "is_claimed": false, "photos": ["https://s3-media4.fl.yelpcdn.com/bphoto/7jSl0Gv4AstLobZ-x4O9mw/o.jpg", "https://s3-media2.fl.yelpcdn.com/bphoto/EO1D_NXPZiMEmSd-wxLbbw/o.jpg", "https://s3-media2.fl.yelpcdn.com/bphoto/CTVj_siPY5nGD48aul4f9Q/o.jpg"], "review_count": 66, "term": "attractions", "url": "https://www.yelp.com/biz/city-of-sunnyvales-baylands-park-sunnyvale?adjust_creative=92p07_JjKyriZTQxAXRiKQ&utm_campaign=yelp_api_v3&utm_medium=api_v3_business_lookup&utm_source=92p07_JjKyriZTQxAXRiKQ", "categories": [{"alias": "parks", "title": "Parks"}], "location": {"address3": "", "zip_code": "94088", "address1": "999 E Caribbean Dr", "state": "CA", "city": "Sunnyvale", "address2": null, "country": "US"}, "is_closed": false, "phone": "+14087307751", "image_url": "https://s3-media2.fl.yelpcdn.com/bphoto/7jSl0Gv4AstLobZ-x4O9mw/o.jpg", "name": "City of Sunnyvale's Baylands Park"}