{"id": "janes-carousel-brooklyn", "rating": 5.0, "coordinates": {"longitude": -73.99243, "latitude": 40.704847}, "is_claimed": true, "hours": [{"is_open_now": false, "open": [{"is_overnight": false, "day": 3, "start": "1100", "end": "1800"}, {"is_overnight": false, "day": 4, "start": "1100", "end": "1800"}, {"is_overnight": false, "day": 5, "start": "1100", "end": "1800"}, {"is_overnight": false, "day": 6, "start": "1100", "end": "1800"}], "hours_type": "REGULAR"}], "photos": ["https://s3-media4.fl.yelpcdn.com/bphoto/Z2FixtfDLc0gubtS_POjZA/o.jpg", "https://s3-media2.fl.yelpcdn.com/bphoto/hkopNkSVA3MbajSqSD9Xfg/o.jpg", "https://s3-media2.fl.yelpcdn.com/bphoto/IKHycQf4PRjnktKyTlhn-w/o.jpg"], "review_count": 102, "term": "attractions", "url": "https://www.yelp.com/biz/janes-carousel-brooklyn?adjust_creative=92p07_JjKyriZTQxAXRiKQ&utm_campaign=yelp_api_v3&utm_medium=api_v3_business_lookup&utm_source=92p07_JjKyriZTQxAXRiKQ", "categories": [{"alias": "carousels", "title": "Carousels"}], "location": {"address3": "", "zip_code": "11201", "address1": "Brooklyn Bridge Park", "address2": "45 Dock St", "city": "Brooklyn", "state": "NY", "country": "US"}, "is_closed": false, "phone": "+17182222502", "image_url": "https://s3-media1.fl.yelpcdn.com/bphoto/Z2FixtfDLc0gubtS_POjZA/o.jpg", "name": "Jane's Carousel"}