{"id": "casbah-club-liverpool", "rating": 5.0, "coordinates": {"longitude": -2.9118931, "latitude": 53.4321747}, "is_claimed": false, "photos": ["https://s3-media1.fl.yelpcdn.com/bphoto/K0drkBPeNFbBxED_F2mrHA/o.jpg", "https://s3-media2.fl.yelpcdn.com/bphoto/skWK8i6oy3p3nCO6v6UKuw/o.jpg", "https://s3-media3.fl.yelpcdn.com/bphoto/2RhOT9GHHhhfgjHgcQ061A/o.jpg"], "review_count": 2, "term": "attractions", "url": "https://www.yelp.com/biz/casbah-club-liverpool?adjust_creative=92p07_JjKyriZTQxAXRiKQ&utm_campaign=yelp_api_v3&utm_medium=api_v3_business_lookup&utm_source=92p07_JjKyriZTQxAXRiKQ", "categories": [{"title": "Museums", "alias": "museums"}], "image_url": "https://s3-media4.fl.yelpcdn.com/bphoto/K0drkBPeNFbBxED_F2mrHA/o.jpg", "is_closed": false, "phone": "+441512803519", "location": {"address3": "", "zip_code": "L12 7JG", "address1": "8 Hayman's Green", "state": "XMS", "city": "Liverpool", "address2": "", "country": "GB"}, "name": "Casbah Club"}