{"id": "la-petite-cr\u00eaperie-melbourne-2", "rating": 4.0, "coordinates": {"longitude": 144.961792, "latitude": -37.8144188}, "is_claimed": false, "hours": [{"is_open_now": true, "open": [{"is_overnight": false, "day": 0, "start": "0900", "end": "1700"}, {"is_overnight": false, "day": 1, "start": "0900", "end": "1700"}, {"is_overnight": false, "day": 2, "start": "0900", "end": "1700"}, {"is_overnight": false, "day": 3, "start": "0900", "end": "1700"}, {"is_overnight": false, "day": 4, "start": "0900", "end": "2130"}, {"is_overnight": false, "day": 5, "start": "0800", "end": "1800"}, {"is_overnight": false, "day": 6, "start": "0800", "end": "1800"}], "hours_type": "REGULAR"}], "photos": ["https://s3-media1.fl.yelpcdn.com/bphoto/uP2-xwRJjEwHtCgD7YiICQ/o.jpg", "https://s3-media1.fl.yelpcdn.com/bphoto/2DagaGi8ooNvo0vYT1sJ3Q/o.jpg", "https://s3-media1.fl.yelpcdn.com/bphoto/1yz2DLVK5L93YhZYTyo5lw/o.jpg"], "review_count": 13, "price": "$$", "term": "restaurants", "url": "https://www.yelp.com/biz/la-petite-cr%C3%AAperie-melbourne-2?adjust_creative=92p07_JjKyriZTQxAXRiKQ&utm_campaign=yelp_api_v3&utm_medium=api_v3_business_lookup&utm_source=92p07_JjKyriZTQxAXRiKQ", "categories": [{"alias": "desserts", "title": "Desserts"}, {"alias": "creperies", "title": "Creperies"}, {"alias": "french", "title": "French"}], "location": {"address3": null, "zip_code": "3000", "address1": "32 Hardware Lane", "address2": null, "city": "Melbourne", "state": "VIC", "country": "AU"}, "is_closed": false, "phone": "+61466406404", "image_url": "https://s3-media2.fl.yelpcdn.com/bphoto/uP2-xwRJjEwHtCgD7YiICQ/o.jpg", "name": "La Petite Cr\u00eaperie"}