{"id": "loba-tours-washington-2", "rating": 3.0, "coordinates": {"longitude": -77.037824, "latitude": 38.9029171}, "is_claimed": true, "hours": [{"is_open_now": false, "open": [{"is_overnight": false, "day": 0, "end": "2030", "start": "0800"}, {"is_overnight": false, "day": 1, "end": "2000", "start": "0800"}, {"is_overnight": false, "day": 2, "end": "2000", "start": "0800"}, {"is_overnight": false, "day": 3, "end": "2000", "start": "0800"}, {"is_overnight": false, "day": 4, "end": "2000", "start": "0800"}, {"is_overnight": false, "day": 5, "end": "2000", "start": "0800"}, {"is_overnight": false, "day": 6, "end": "2000", "start": "0800"}], "hours_type": "REGULAR"}], "photos": ["https://s3-media2.fl.yelpcdn.com/bphoto/GiQ20hO2BdtyLKpfR9cw7Q/o.jpg", "https://s3-media2.fl.yelpcdn.com/bphoto/XF2cDNxNAlIjlRG-6z2cVA/o.jpg"], "review_count": 2, "term": "attractions", "url": "https://www.yelp.com/biz/loba-tours-washington-2?adjust_creative=92p07_JjKyriZTQxAXRiKQ&utm_campaign=yelp_api_v3&utm_medium=api_v3_business_lookup&utm_source=92p07_JjKyriZTQxAXRiKQ", "categories": [{"alias": "tours", "title": "Tours"}], "location": {"address3": null, "zip_code": "20006", "address1": "1629 K St NW", "state": "DC", "city": "Washington", "address2": "Ste 300", "country": "US"}, "is_closed": false, "phone": "+12025365737", "image_url": "https://s3-media2.fl.yelpcdn.com/bphoto/GiQ20hO2BdtyLKpfR9cw7Q/o.jpg", "name": "Loba Tours"}