{"id": "bcs-george-forbes-house-queanbeyan", "rating": 0.0, "coordinates": {"longitude": 149.2326202, "latitude": -35.3468285}, "is_claimed": false, "photos": [], "review_count": 0, "term": "hotels", "url": "https://www.yelp.com/biz/bcs-george-forbes-house-queanbeyan?adjust_creative=92p07_JjKyriZTQxAXRiKQ&utm_campaign=yelp_api_v3&utm_medium=api_v3_business_lookup&utm_source=92p07_JjKyriZTQxAXRiKQ", "categories": [{"alias": "hostels", "title": "Hostels"}], "location": {"address3": null, "zip_code": "2620", "address1": "Cnr Erin & Collett Sts", "state": "NSW", "city": "Queanbeyan", "address2": null, "country": "AU"}, "is_closed": false, "phone": "+61261519600", "image_url": "", "name": "BCS George Forbes House"}