{"id": "lion-habitat-ranch-henderson", "rating": 4.5, "coordinates": {"longitude": -115.1547057, "latitude": 35.952935}, "is_claimed": true, "hours": [{"is_open_now": false, "open": [{"is_overnight": false, "day": 0, "start": "1100", "end": "1400"}, {"is_overnight": false, "day": 4, "start": "1100", "end": "1400"}, {"is_overnight": false, "day": 5, "start": "1100", "end": "1400"}, {"is_overnight": false, "day": 6, "start": "1100", "end": "1400"}], "hours_type": "REGULAR"}], "photos": ["https://s3-media1.fl.yelpcdn.com/bphoto/-FPk1QRPOt0gzRqtS8pGaA/o.jpg", "https://s3-media3.fl.yelpcdn.com/bphoto/49638ZurgUfBop9Rgg923A/o.jpg", "https://s3-media2.fl.yelpcdn.com/bphoto/jWx6bHFuExt4Q0ycEW-8BA/o.jpg"], "review_count": 124, "term": "attractions", "url": "https://www.yelp.com/biz/lion-habitat-ranch-henderson?adjust_creative=92p07_JjKyriZTQxAXRiKQ&utm_campaign=yelp_api_v3&utm_medium=api_v3_business_lookup&utm_source=92p07_JjKyriZTQxAXRiKQ", "categories": [{"title": "Zoos", "alias": "zoos"}, {"title": "Tours", "alias": "tours"}], "image_url": "https://s3-media2.fl.yelpcdn.com/bphoto/-FPk1QRPOt0gzRqtS8pGaA/o.jpg", "is_closed": false, "phone": "+17025956666", "location": {"address3": "", "zip_code": "89044", "address1": "12175 Bermuda Rd", "state": "NV", "city": "Henderson", "address2": "", "country": "US"}, "name": "Lion Habitat Ranch"}