{"price": "$$", "rating": 4.0, "coordinates": {"longitude": -87.6236184577346, "latitude": 41.8919021875965}, "is_claimed": true, "hours": [{"is_open_now": false, "open": [{"is_overnight": false, "end": "2200", "start": "1100", "day": 0}, {"is_overnight": false, "end": "2200", "start": "1100", "day": 1}, {"is_overnight": false, "end": "2200", "start": "1100", "day": 2}, {"is_overnight": false, "end": "2200", "start": "1100", "day": 3}, {"is_overnight": false, "end": "2300", "start": "1100", "day": 4}, {"is_overnight": false, "end": "2300", "start": "1100", "day": 5}, {"is_overnight": false, "end": "2200", "start": "1100", "day": 6}], "hours_type": "REGULAR"}], "photos": ["https://s3-media1.fl.yelpcdn.com/bphoto/kQ7z4THSnGGXwJTVN_VgZw/o.jpg", "https://s3-media3.fl.yelpcdn.com/bphoto/ITkh79KBWTRRTt_BaWBSWQ/o.jpg", "https://s3-media1.fl.yelpcdn.com/bphoto/pdp4HAKqDhvXGVviKPHnSw/o.jpg"], "review_count": 1381, "id": "bandera-restaurant-chicago", "term": "restaurants", "url": "https://www.yelp.com/biz/bandera-restaurant-chicago?adjust_creative=92p07_JjKyriZTQxAXRiKQ&utm_campaign=yelp_api_v3&utm_medium=api_v3_business_lookup&utm_source=92p07_JjKyriZTQxAXRiKQ", "categories": [{"alias": "jazzandblues", "title": "Jazz & Blues"}, {"alias": "newamerican", "title": "American (New)"}], "location": {"address3": "", "zip_code": "60611", "address1": "535 N Michigan Ave", "state": "IL", "city": "Chicago", "address2": "", "country": "US"}, "is_closed": false, "phone": "+13126443524", "image_url": "https://s3-media3.fl.yelpcdn.com/bphoto/kQ7z4THSnGGXwJTVN_VgZw/o.jpg", "name": "Bandera Restaurant"}