{"price": "$", "rating": 4.0, "coordinates": {"longitude": -71.1184930801392, "latitude": 42.3735419007205}, "is_claimed": true, "hours": [{"is_open_now": false, "open": [{"is_overnight": false, "end": "2200", "start": "0800", "day": 0}, {"is_overnight": false, "end": "2200", "start": "0800", "day": 1}, {"is_overnight": false, "end": "2200", "start": "0800", "day": 2}, {"is_overnight": false, "end": "2200", "start": "0800", "day": 3}, {"is_overnight": false, "end": "2000", "start": "0800", "day": 4}], "hours_type": "REGULAR"}], "photos": ["https://s3-media3.fl.yelpcdn.com/bphoto/Ggy2IhzyndcGzrNxuqYvpA/o.jpg", "https://s3-media3.fl.yelpcdn.com/bphoto/jUAtjhu8h2nIW5GiWNFWRg/o.jpg", "https://s3-media4.fl.yelpcdn.com/bphoto/JzSqmt5WkXC99go9K5ZgSQ/o.jpg"], "review_count": 11, "id": "caf\u00e9-gato-rojo-cambridge-2", "term": "attractions", "url": "https://www.yelp.com/biz/caf%C3%A9-gato-rojo-cambridge-2?adjust_creative=92p07_JjKyriZTQxAXRiKQ&utm_campaign=yelp_api_v3&utm_medium=api_v3_business_lookup&utm_source=92p07_JjKyriZTQxAXRiKQ", "categories": [{"title": "Coffee & Tea", "alias": "coffee"}, {"title": "Art Galleries", "alias": "galleries"}, {"title": "Music Venues", "alias": "musicvenues"}], "image_url": "https://s3-media2.fl.yelpcdn.com/bphoto/Ggy2IhzyndcGzrNxuqYvpA/o.jpg", "is_closed": false, "phone": "+16174964658", "location": {"address3": "", "zip_code": "02138", "address1": "Basement of Dudley Lehman Hall, Harvard Yard", "address2": "", "city": "Cambridge", "state": "MA", "country": "US"}, "name": "Caf\u00e9 Gato Rojo"}