{"price": "$", "rating": 4.0, "coordinates": {"longitude": -86.772877, "latitude": 33.4243542}, "is_claimed": false, "hours": [{"is_open_now": false, "open": [{"is_overnight": false, "day": 0, "start": "0700", "end": "2000"}, {"is_overnight": false, "day": 1, "start": "0700", "end": "2000"}, {"is_overnight": false, "day": 2, "start": "0700", "end": "2000"}, {"is_overnight": false, "day": 3, "start": "0700", "end": "2000"}, {"is_overnight": false, "day": 4, "start": "0700", "end": "2000"}, {"is_overnight": false, "day": 5, "start": "0800", "end": "1800"}], "hours_type": "REGULAR"}], "photos": ["https://s3-media1.fl.yelpcdn.com/bphoto/1iRSOHT9IAvZj05AuKGksQ/o.jpg", "https://s3-media1.fl.yelpcdn.com/bphoto/PMhURBtuaQwoBDjUIvVucQ/o.jpg"], "review_count": 12, "id": "everything-iz-birmingham", "term": "restaurants", "url": "https://www.yelp.com/biz/everything-iz-birmingham?adjust_creative=92p07_JjKyriZTQxAXRiKQ&utm_campaign=yelp_api_v3&utm_medium=api_v3_business_lookup&utm_source=92p07_JjKyriZTQxAXRiKQ", "categories": [{"alias": "cafes", "title": "Cafes"}], "location": {"address3": "", "zip_code": "35243", "address1": "3325 Rocky Ridge Plz", "address2": "", "city": "Birmingham", "state": "AL", "country": "US"}, "is_closed": false, "phone": "+12059797570", "image_url": "https://s3-media4.fl.yelpcdn.com/bphoto/1iRSOHT9IAvZj05AuKGksQ/o.jpg", "name": "Everything Iz"}