{"price": "$$", "rating": 3.5, "coordinates": {"longitude": 144.96057108018, "latitude": -37.8129778794208}, "is_claimed": false, "photos": ["https://s3-media3.fl.yelpcdn.com/bphoto/rfAne65Hi15-TuXFoEHcgg/o.jpg", "https://s3-media1.fl.yelpcdn.com/bphoto/zpgMCoNIT1DBdb1mzyFOaA/o.jpg", "https://s3-media2.fl.yelpcdn.com/bphoto/03KJn4yJ2SSsM2bAjzKI4g/o.jpg"], "review_count": 10, "id": "mook-ji-bar-melbourne", "term": "restaurants", "url": "https://www.yelp.com/biz/mook-ji-bar-melbourne?adjust_creative=92p07_JjKyriZTQxAXRiKQ&utm_campaign=yelp_api_v3&utm_medium=api_v3_business_lookup&utm_source=92p07_JjKyriZTQxAXRiKQ", "categories": [{"title": "Korean", "alias": "korean"}], "image_url": "https://s3-media4.fl.yelpcdn.com/bphoto/rfAne65Hi15-TuXFoEHcgg/o.jpg", "is_closed": false, "phone": "", "location": {"address3": "", "zip_code": "3000", "address1": "419 Lonsdale St", "address2": "", "city": "Melbourne", "state": "VIC", "country": "AU"}, "name": "Mook Ji Bar"}